aiocometd/__init__.py
aiocometd/_metadata.py
aiocometd/client.py
aiocometd/constants.py
aiocometd/exceptions.py
aiocometd/extensions.py
aiocometd/py.typed
aiocometd/typing.py
aiocometd/utils.py
aiocometd/transports/__init__.py
aiocometd/transports/abc.py
aiocometd/transports/base.py
aiocometd/transports/long_polling.py
aiocometd/transports/registry.py
aiocometd/transports/websocket.py
tastyworks_aiocometd-1.0.dist-info/LICENSE.txt
tastyworks_aiocometd-1.0.dist-info/METADATA
tastyworks_aiocometd-1.0.dist-info/WHEEL
tastyworks_aiocometd-1.0.dist-info/top_level.txt
tastyworks_aiocometd-1.0.dist-info/RECORD
